the_atlas_project/__init__.py
the_atlas_project/atlas_reader.py
the_atlas_project-1.0.1.dist-info/METADATA
the_atlas_project-1.0.1.dist-info/WHEEL
the_atlas_project-1.0.1.dist-info/top_level.txt
the_atlas_project-1.0.1.dist-info/RECORD
