Metadata-Version: 2.4
Name: the-atlas-project
Version: 1.0.1
Summary: A simple atlasting system for Raylib-py
Author: DDev
License: MIT
Project-URL: Homepage, https://github.com/Jacketdude/the-atlas-project
Project-URL: Repository, https://github.com/Jacketdude/the-atlas-project
Requires-Dist: raylib-py
